dicomgenerator/__init__.py
dicomgenerator/annotation.py
dicomgenerator/cli.py
dicomgenerator/dicom.py
dicomgenerator/exceptions.py
dicomgenerator/export.py
dicomgenerator/generators.py
dicomgenerator/logging.py
dicomgenerator/persistence.py
dicomgenerator/resources/__init__.py
dicomgenerator/resources/skeleton.jpg
dicomgenerator/resources/skeleton_tiny.jpg
dicomgenerator/resources/templates/ct_toshiba_aquilion.json
dicomgenerator/resources/templates/ct_toshiba_aquilion.txt
dicomgenerator/settings.py
dicomgenerator/templates.py
dicomgenerator/tools.py
dicomgenerator-0.9.1.dist-info/LICENSE
dicomgenerator-0.9.1.dist-info/METADATA
dicomgenerator-0.9.1.dist-info/WHEEL
dicomgenerator-0.9.1.dist-info/entry_points.txt
dicomgenerator-0.9.1.dist-info/RECORD
