Metadata-Version: 2.3
Name: dicomgenerator
Version: 0.9.1
Summary: Generate pydicom datasets and data elements for use in testing
License: MIT
Author: sjoerdk
Author-email: sjoerd.kerkstra@radboudumc.nl
Requires-Python: >=3.12,<4.0
Classifier: License :: OSI Approved :: MIT License
Classifier: Programming Language :: Python :: 3
Classifier: Programming Language :: Python :: 3.12
Classifier: Programming Language :: Python :: 3.13
Requires-Dist: click (>=8.1.7,<9.0.0)
Requires-Dist: factory-boy (>=3.2.1,<4.0.0)
Requires-Dist: numpy (>=2.3.1,<3.0.0)
Requires-Dist: pillow (>=11.2.1,<12.0.0)
Requires-Dist: pydicom (>=3.0.1,<4.0.0)
Project-URL: Repository, https://github.com/sjoerdk/dicomgenerator
